razorthink/__init__.py
razorthink-0.0.1.dist-info/METADATA
razorthink-0.0.1.dist-info/WHEEL
razorthink-0.0.1.dist-info/top_level.txt
razorthink-0.0.1.dist-info/RECORD
