Metadata-Version: 2.1
Name: razorthink
Version: 0.0.1
Summary: Razor SDK for Razorthink AI
Home-page: https://razorthink.com
Author: Razorthink
Author-email: sandeep.kumar@razorthink.com
License: UNKNOWN
Platform: UNKNOWN
Requires-Python: >=3.7
